nectar/__init__.py
nectar/account.py
nectar/amount.py
nectar/asciichart.py
nectar/asset.py
nectar/block.py
nectar/blockchain.py
nectar/blockchaininstance.py
nectar/blockchainobject.py
nectar/cli.py
nectar/comment.py
nectar/community.py
nectar/constants.py
nectar/discussions.py
nectar/exceptions.py
nectar/haf.py
nectar/hive.py
nectar/imageuploader.py
nectar/instance.py
nectar/market.py
nectar/memo.py
nectar/message.py
nectar/nodelist.py
nectar/price.py
nectar/profile.py
nectar/py.typed
nectar/rc.py
nectar/snapshot.py
nectar/storage.py
nectar/transactionbuilder.py
nectar/utils.py
nectar/version.py
nectar/vote.py
nectar/wallet.py
nectar/witness.py
nectarapi/__init__.py
nectarapi/exceptions.py
nectarapi/graphenerpc.py
nectarapi/node.py
nectarapi/noderpc.py
nectarapi/openapi.py
nectarapi/py.typed
nectarapi/rpcutils.py
nectarapi/version.py
nectarbase/__init__.py
nectarbase/ledgertransactions.py
nectarbase/memo.py
nectarbase/objects.py
nectarbase/objecttypes.py
nectarbase/operationids.py
nectarbase/operations.py
nectarbase/py.typed
nectarbase/signedtransactions.py
nectarbase/transactions.py
nectarbase/version.py
nectargraphenebase/__init__.py
nectargraphenebase/account.py
nectargraphenebase/aes.py
nectargraphenebase/base58.py
nectargraphenebase/bip32.py
nectargraphenebase/bip38.py
nectargraphenebase/chains.py
nectargraphenebase/dictionary.py
nectargraphenebase/ecdsasig.py
nectargraphenebase/objects.py
nectargraphenebase/objecttypes.py
nectargraphenebase/operationids.py
nectargraphenebase/operations.py
nectargraphenebase/prefix.py
nectargraphenebase/py.typed
nectargraphenebase/signedtransactions.py
nectargraphenebase/types.py
nectargraphenebase/unsignedtransactions.py
nectargraphenebase/version.py
nectarstorage/__init__.py
nectarstorage/base.py
nectarstorage/exceptions.py
nectarstorage/interfaces.py
nectarstorage/masterpassword.py
nectarstorage/py.typed
nectarstorage/ram.py
nectarstorage/sqlite.py
hive_nectar-0.2.14.dist-info/METADATA
hive_nectar-0.2.14.dist-info/WHEEL
hive_nectar-0.2.14.dist-info/entry_points.txt
hive_nectar-0.2.14.dist-info/licenses/LICENSE.txt
hive_nectar-0.2.14.dist-info/RECORD
