Metadata-Version: 2.4
Name: hive-nectar
Version: 0.2.14
Summary: Hive Blockchain Python Library
Project-URL: Homepage, http://www.github.com/thecrazygm/hive-nectar
Project-URL: Download, https://github.com/thecrazygm/hive-nectar/tarball/0.1.0b
Project-URL: Bug Tracker, https://github.com/thecrazygm/hive-nectar/issues
Author-email: Michael Garcia <thecrazygm@gmail.com>
Maintainer-email: Michael Garcia <thecrazygm@gmail.com>
License: The MIT License (MIT)
License-File: LICENSE.txt
Keywords: api,hive,library,rpc
Classifier: Development Status :: 4 - Beta
Classifier: Intended Audience :: Developers
Classifier: Intended Audience :: Financial and Insurance Industry
Classifier: License :: OSI Approved :: MIT License
Classifier: Operating System :: OS Independent
Classifier: Programming Language :: Python
Classifier: Programming Language :: Python :: 3
Classifier: Programming Language :: Python :: 3.10
Classifier: Programming Language :: Python :: 3.11
Classifier: Programming Language :: Python :: 3.12
Classifier: Programming Language :: Python :: 3.13
Classifier: Topic :: Office/Business :: Financial
Requires-Python: >=3.10
Requires-Dist: appdirs
Requires-Dist: asn1crypto
Requires-Dist: click
Requires-Dist: cryptography
Requires-Dist: diff-match-patch
Requires-Dist: ecdsa
Requires-Dist: httpx>=0.28.1
Requires-Dist: prettytable
Requires-Dist: pycryptodomex
Requires-Dist: requests>=2.32.4
Requires-Dist: ruamel-yaml
Requires-Dist: scrypt
Requires-Dist: types-requests
